<?xml version="1.0" encoding="UTF-8" standalone="yes"?>
<ns2:listCategory xmlns="http://www.coffeeShop.com.vn" xmlns:ns2="jaxb.listcategory">
    <category>
        <id>1</id>
        <name>Cà phê</name>
        <product>
            <id>1</id>
            <name>Cà phê đen đá</name>
            <productItem>
                <price>12.0</price>
                <competitorName>Dù Vàng</competitorName>
            </productItem>
            <productItem>
                <price>14.0</price>
                <competitorName>Uni Space</competitorName>
            </productItem>
        </product>
        <product>
            <id>2</id>
            <name>Cà phê đen nóng</name>
            <productItem>
                <price>16.0</price>
                <competitorName>Dù Vàng</competitorName>
            </productItem>
            <productItem>
                <price>18.0</price>
                <competitorName>Uni Space</competitorName>
            </productItem>
        </product>
    </category>
    <category>
        <id>2</id>
        <name>Trà</name>
        <product>
            <id>3</id>
            <name>Trà đào</name>
            <productItem>
                <price>20.0</price>
                <competitorName>Dù Vàng</competitorName>
            </productItem>
            <productItem>
                <price>22.0</price>
                <competitorName>Uni Space</competitorName>
            </productItem>
        </product>
        <product>
            <id>4</id>
            <name>Trà xoài</name>
            <productItem>
                <price>20.0</price>
                <competitorName>Dù Vàng</competitorName>
            </productItem>
            <productItem>
                <price>22.0</price>
                <competitorName>Uni Space</competitorName>
            </productItem>
        </product>
    </category>
    <category>
        <id>3</id>
        <name>Yogust</name>
        <product>
            <id>5</id>
            <name>Yogust đào</name>
            <productItem>
                <price>20.0</price>
                <competitorName>Dù Vàng</competitorName>
            </productItem>
            <productItem>
                <price>22.0</price>
                <competitorName>Uni Space</competitorName>
            </productItem>
        </product>
        <product>
            <id>6</id>
            <name>Yogust xoài</name>
            <productItem>
                <price>20.0</price>
                <competitorName>Uni Space</competitorName>
            </productItem>
            <productItem>
                <price>22.0</price>
                <competitorName>Dù Vàng</competitorName>
            </productItem>
        </product>
    </category>
</ns2:listCategory>
